setup.py
DecisionBoundary/DecisionBoundary.py
DecisionBoundary/__init__.py
DecisionBoundary.egg-info/PKG-INFO
DecisionBoundary.egg-info/SOURCES.txt
DecisionBoundary.egg-info/dependency_links.txt
DecisionBoundary.egg-info/not-zip-safe
DecisionBoundary.egg-info/top_level.txt