Metadata-Version: 1.0
Name: DecisionBoundary
Version: 0.1.2
Summary: plot decision boundary
Home-page: UNKNOWN
Author: UNKNOWN
Author-email: UNKNOWN
License: UNKNOWN
Platform: UNKNOWN
